env_get/__init__.py
env_get/env.py
env_get/py.typed
env_get-1.1.0.dist-info/LICENSE
env_get-1.1.0.dist-info/METADATA
env_get-1.1.0.dist-info/WHEEL
env_get-1.1.0.dist-info/top_level.txt
env_get-1.1.0.dist-info/RECORD
