Metadata-Version: 2.1
Name: env-get
Version: 1.1.0
Summary: Manage and get process.env
Author-email: Kael Zhang <i+pypi@kael.me>
License: Copyright (c) 2013 kaelzhang <>, contributors
Project-URL: Homepage, https://github.com/kaelzhang/python-env-get
Keywords: env-get,env,process.env,environment variable
Classifier: Topic :: Software Development :: Libraries :: Python Modules
Classifier: Programming Language :: Python :: 3.7
Classifier: Programming Language :: Python :: 3.8
Classifier: Programming Language :: Python :: 3.9
Classifier: Programming Language :: Python :: 3.10
Classifier: Programming Language :: Python :: 3.11
Classifier: Programming Language :: Python :: 3.12
Classifier: Programming Language :: Python :: Implementation :: PyPy
Classifier: Topic :: Software Development :: Libraries :: Python Modules
Classifier: License :: OSI Approved :: MIT License
Requires-Python: >=3
License-File: LICENSE
Provides-Extra: dev
Requires-Dist: coverage; extra == "dev"
Requires-Dist: ruff; extra == "dev"
Requires-Dist: pytest; extra == "dev"
Requires-Dist: pytest-cov; extra == "dev"
Requires-Dist: twine; extra == "dev"
Requires-Dist: mypy; extra == "dev"
Requires-Dist: build; extra == "dev"
